[
    {
        "Danh mục": "1. Doanh thu bán hàng và cung cấp dịch vụ",
        "2021": "",
        "2022": "",
        "2023": ""
    },
    {
        "Danh mục": "2. Các khoản giảm trừ doanh thu",
        "2021": "",
        "2022": "",
        "2023": ""
    },
    {
        "Danh mục": "3. Doanh thu thuần về bán hàng và cung cấp dịch vụ (10 = 01 - 02)",
        "2021": "4,343,731,000,000",
        "2022": "4,499,949,000,000",
        "2023": "6,459,693,986,629"
    },
    {
        "Danh mục": "4. Giá vốn hàng bán",
        "2021": "2,540,485,000,000",
        "2022": "2,332,574,000,000",
        "2023": "4,025,577,907,573"
    },
    {
        "Danh mục": "5. Lợi nhuận gộp về bán hàng và cung cấp dịch vụ(20=10-11)",
        "2021": "",
        "2022": "",
        "2023": "4,697,361,538,165"
    },
    {
        "Danh mục": "6. Doanh thu hoạt động tài chính",
        "2021": "18,415,382,000,000",
        "2022": "20,436,426,000,000",
        "2023": "18,190,866,407,908"
    },
    {
        "Danh mục": "7. Chi phí tài chính",
        "2021": "363,132,000,000",
        "2022": "286,049,000,000",
        "2023": "187,063,950,289"
    },
    {
        "Danh mục": "- Trong đó: Chi phí lãi vay",
        "2021": "5,137",
        "2022": "5,725",
        "2023": ""
    },
    {
        "Danh mục": "8. Phần lãi lỗ trong công ty liên doanh, liên kết",
        "2021": "",
        "2022": "",
        "2023": ""
    },
    {
        "Danh mục": "9. Chi phí bán hàng",
        "2021": "",
        "2022": "",
        "2023": ""
    },
    {
        "Danh mục": "10. Chi phí quản lý doanh nghiệp",
        "2021": "",
        "2022": "",
        "2023": ""
    },
    {
        "Danh mục": "11. Lợi nhuận thuần từ hoạt động kinh doanh{30=20+(21-22) + 24 - (25+26)}",
        "2021": "",
        "2022": "",
        "2023": ""
    },
    {
        "Danh mục": "12. Thu nhập khác",
        "2021": "",
        "2022": "",
        "2023": ""
    },
    {
        "Danh mục": "13. Chi phí khác",
        "2021": "",
        "2022": "",
        "2023": ""
    },
    {
        "Danh mục": "14. Lợi nhuận khác(40=31-32)",
        "2021": "",
        "2022": "",
        "2023": ""
    },
    {
        "Danh mục": "15. Tổng lợi nhuận kế toán trước thuế(50=30+40)",
        "2021": "",
        "2022": "",
        "2023": ""
    },
    {
        "Danh mục": "16. Chi phí thuế TNDN hiện hành",
        "2021": "",
        "2022": "",
        "2023": ""
    },
    {
        "Danh mục": "17. Chi phí thuế TNDN hoãn lại",
        "2021": "",
        "2022": "",
        "2023": ""
    },
    {
        "Danh mục": "18. Lợi nhuận sau thuế thu nhập doanh nghiệp(60=50-51-52)",
        "2021": "",
        "2022": "",
        "2023": ""
    },
    {
        "Danh mục": "19. Lợi nhuận sau thuế công ty mẹ",
        "2021": "",
        "2022": "",
        "2023": ""
    },
    {
        "Danh mục": "20. Lợi nhuận sau thuế công ty mẹ không kiểm soát",
        "2021": "",
        "2022": "",
        "2023": ""
    },
    {
        "Danh mục": "21. Lãi cơ bản trên cổ phiếu(*)",
        "2021": "",
        "2022": "",
        "2023": ""
    },
    {
        "Danh mục": "22. Lãi suy giảm trên cổ phiếu (*)",
        "2021": "",
        "2022": "",
        "2023": ""
    }
]